yamlwrap/__init__.py
yamlwrap/__main__.py
yamlwrap-2.1.1.dist-info/LICENSE
yamlwrap-2.1.1.dist-info/METADATA
yamlwrap-2.1.1.dist-info/WHEEL
yamlwrap-2.1.1.dist-info/top_level.txt
yamlwrap-2.1.1.dist-info/RECORD
