Metadata-Version: 2.1
Name: yamlwrap
Version: 2.1.1
Summary: VCS-friendly documents in YAML
Author-email: Viktor Eikman <viktor.eikman@gmail.com>
License: GPL-3.0-only
Project-URL: Homepage, https://github.com/veikman/yamlwrap
Classifier: Development Status :: 5 - Production/Stable
Classifier: Intended Audience :: Developers
Classifier: Intended Audience :: System Administrators
Classifier: License :: OSI Approved :: GNU General Public License v3 (GPLv3)
Classifier: Operating System :: OS Independent
Classifier: Programming Language :: Python :: 3
Classifier: Topic :: Database
Classifier: Topic :: Software Development :: Libraries :: Python Modules
Classifier: Topic :: Software Development :: Version Control
Classifier: Topic :: Text Editors
Requires-Python: >=3.8
License-File: LICENSE
Requires-Dist: PyYaml
Requires-Dist: punwrap
Requires-Dist: pyaml
Provides-Extra: testing
Requires-Dist: pytest ; extra == 'testing'
